{
  "options": [{
    "key": "titleLanguage",
    "default": "romaji",
    "options": [ "english", "native" ],
    "label": "Title language (overridden if authenticated)"
  }, {
    "key": "barsEnable",
    "default": true,
    "label": "Enable progress bars"
  }, {
    "key": "insertIndex",
    "default": 1,
    "label": "Progress bars position in page"
  }, {
    "key": "barsCount",
    "default": 5,
    "label": "No. of progress bars"
  }, {
    "key": "barsSeparateByType",
    "default": false,
    "label": "Separate anime and manga progress bars"
  }, {
    "key": "cardsEnable",
    "default": true,
    "label": "Enable infocards"
  }, {
    "key": "cardsHoverTimeout",
    "default": 500,
    "label": "Infocard hover timeout (ms)"
  }, {
    "key": "notifContentEnable",
    "default": true,
    "label": "Enable notification content preview"
  }, {
    "key": "notifsEnable",
    "default": true,
    "label": "Enable notifications (authentication required)"
  }, {
    "key": "notifsUnreadResetOnQuery",
    "default": false,
    "label": "Reset unread notification count when new notification received"
  }, {
    "key": "updateCheckEnable",
    "default": false,
    "label": "Periodically check for extension updates"
  }]
}
